mpi4py_utilities/__init__.py
mpi4py_utilities/world1D.py
mpi4py_utilities/world2D.py
mpi4py_utilities/world3D.py
mpi4py_utilities-1.0.2.dist-info/LICENSE.txt
mpi4py_utilities-1.0.2.dist-info/METADATA
mpi4py_utilities-1.0.2.dist-info/WHEEL
mpi4py_utilities-1.0.2.dist-info/top_level.txt
mpi4py_utilities-1.0.2.dist-info/RECORD
